bcc2to/__init__.py
bcc2to/__main__.py
bcc2to/parts/__init__.py
bcc2to/parts/cleanup.py
bcc2to/parts/install.py
bcc2to/parts/proxy.py
bcc2to/parts/smtpd.py
bcc2to/parts/smtplib.py
bcc2to-0.4.0rc2.dist-info/DESCRIPTION.rst
bcc2to-0.4.0rc2.dist-info/METADATA
bcc2to-0.4.0rc2.dist-info/RECORD
bcc2to-0.4.0rc2.dist-info/WHEEL
bcc2to-0.4.0rc2.dist-info/metadata.json
bcc2to-0.4.0rc2.dist-info/top_level.txt
