Metadata-Version: 2.0
Name: bcc2to
Version: 0.4.0rc2
Summary: Posfix plugin for individual list mail delivering
Home-page: UNKNOWN
Author: Vidmantas Balčytis
Author-email: vidma@lema.lt
License: UNKNOWN
Keywords: postfix mail plugin
Platform: UNKNOWN
Classifier: Development Status :: 3 - Alpha
Classifier: Environment :: Plugins
Classifier: Intended Audience :: System Administrators
Classifier: Topic :: Communications :: Email :: Mailing List Servers
Classifier: License :: Free for non-commercial use
Classifier: Programming Language :: Python :: 3.4
Classifier: Programming Language :: Python :: 3.5
Classifier: Programming Language :: Python :: 3.6
